wexample_helpers_yaml-0.0.113.dist-info/METADATA
wexample_helpers_yaml-0.0.113.dist-info/WHEEL
wexample_helpers_yaml-0.0.113.dist-info/entry_points.txt
wexample_helpers_yaml/__init__.py
wexample_helpers_yaml/__pycache__/__init__.py
wexample_helpers_yaml/classes/__init__.py
wexample_helpers_yaml/classes/__pycache__/__init__.py
wexample_helpers_yaml/classes/mixin/__init__.py
wexample_helpers_yaml/classes/mixin/__pycache__/__init__.py
wexample_helpers_yaml/classes/mixin/has_yaml_env_keys_file.py
wexample_helpers_yaml/const/__init__.py
wexample_helpers_yaml/const/types.py
wexample_helpers_yaml/helpers/__init__.py
wexample_helpers_yaml/helpers/__pycache__/__init__.py
wexample_helpers_yaml/helpers/yaml_helpers.py
wexample_helpers_yaml/py.typed
wexample_helpers_yaml/tests/__init__.py
wexample_helpers_yaml-0.0.113.dist-info/RECORD
