Metadata-Version: 2.1
Name: wexample-helpers-yaml
Version: 0.0.113
Summary: Helpers for reading yaml files.
Author-Email: weeger <contact@wexample.com>
License: MIT
Classifier: Programming Language :: Python :: 3
Classifier: License :: OSI Approved :: MIT License
Classifier: Operating System :: OS Independent
Project-URL: homepage, https://github.com/wexample/python-helpers-yaml
Requires-Python: >=3.10
Requires-Dist: attrs>=23.1.0
Requires-Dist: cattrs>=23.1.0
Requires-Dist: pyyaml
Requires-Dist: wexample-helpers==0.0.88
Provides-Extra: dev
Requires-Dist: pytest; extra == "dev"
Requires-Dist: pytest-cov; extra == "dev"
